fsm_wagtail/__init__.py
fsm_wagtail/admin.py
fsm_wagtail/apps.py
fsm_wagtail/models.py
fsm_wagtail/tests.py
fsm_wagtail/views.py
django_fsm_wagtail-0.1.0.dist-info/LICENSE
django_fsm_wagtail-0.1.0.dist-info/METADATA
django_fsm_wagtail-0.1.0.dist-info/WHEEL
django_fsm_wagtail-0.1.0.dist-info/top_level.txt
django_fsm_wagtail-0.1.0.dist-info/RECORD
