Metadata-Version: 2.1
Name: django-fsm-wagtail
Version: 0.1.0
Summary: A Django app to integrate django-fsm to wagtail admin.
Home-page: https://github.com/abahnihi/django-fsm-wagtail
Author: Ahmed ElBahnihi
Author-email: abahnihi@gmail.com
License: MIT
Keywords: fsm_wagtail
Platform: UNKNOWN
Classifier: Development Status :: 3 - Alpha
Classifier: Framework :: Django :: 2.2
Classifier: Intended Audience :: Developers
Classifier: License :: OSI Approved :: BSD License
Classifier: Natural Language :: English
Classifier: Programming Language :: Python :: 2
Classifier: Programming Language :: Python :: 2.7
Classifier: Programming Language :: Python :: 3
Classifier: Programming Language :: Python :: 3.5
Classifier: Programming Language :: Python :: 3.6
